{
  "_class": "symbolInstance",
  "booleanOperation": -1,
  "clippingMaskMode": 0,
  "do_objectID": "F1986767-DD06-43B1-91A9-CC41B6B6588F",
  "exportOptions": {
    "_class": "exportOptions",
    "do_objectID": "67C5E94A-1D0C-4565-8AC9-3F7A0C607C61",
    "exportFormats": [
    ],
    "includedLayerIds": [
    ],
    "layerOptions": 0,
    "shouldTrim": false
  },
  "frame": {
    "_class": "rect",
    "constrainProportions": false,
    "do_objectID": "F513427A-0C2B-4FC0-9C84-CFE1DE94751E",
    "height": 50,
    "width": 379,
    "x": 0,
    "y": -1
  },
  "hasClippingMask": false,
  "horizontalSpacing": 0,
  "isFixedToViewport": false,
  "isFlippedHorizontal": false,
  "isFlippedVertical": false,
  "isLocked": false,
  "isVisible": true,
  "layerListExpandedType": 0,
  "name": "molecule / mobile header",
  "nameIsFixed": false,
  "overrideValues": [
  ],
  "resizingConstraint": 63,
  "resizingType": 0,
  "rotation": 0,
  "scale": 1,
  "shouldBreakMaskChain": false,
  "style": {
    "_class": "style",
    "do_objectID": "CDD86055-EBE3-4D1F-80E0-C6EC289F805A",
    "endMarkerType": 0,
    "miterLimit": 10,
    "startMarkerType": 0,
    "windingRule": 1
  },
  "symbolID": "8AD02C82-865D-4049-9640-F64450C5ED69",
  "verticalSpacing": 0
}